Vending machine/design.sv
// Code your design here
module vending_machine(can_despatch,clk,coin,rst);
   output   can_despatch;
   input [1:0] coin;
   input       clk,rst;
   reg [1:0]   state;
   reg [1:0]   next_state;
   parameter  s0=0;
   parameter  s5=1;
   parameter  s10=2;
   parameter  s15=3;

   always @(posedge clk)
     begin
       if (rst)
         state=s0;
       else
         state=next_state;
     end
always @(state,coin)
     begin
    case (state)
s0:  begin
           if (coin==2'b00)
        next_state=s0;
           else
       if (coin==2'b01)
          next_state=s5;
       else
         if (coin==2'b10)
          next_state=s10;
        end
 s5:   begin
       if (coin==2'b00)
          next_state=s5;
       else
         if (coin==2'b01)
            next_state=s10;
         else
           if (coin==2'b10)
             next_state=s15;
             end    
s10:  begin
           if (coin==2'b00)
        next_state=s10;
           else
       if (coin==2'b01)
          next_state=s15;
       else
        if (coin==2'b10)
            next_state=s15;  
           end
       s15:	begin
           if (coin==2'b00)
        next_state=s0;
           else
       if (coin==2'b01)
          next_state=s5;
       else
        if (coin==2'b10)
            next_state=s10;  
           end         
default : next_state=s0;   
    endcase // case (state)
     end 	// always @

assign can_despatch = (state==s15) ? 1 : 0; 

endmodule

Vending machine/testbench.sv
// Code your testbench here
// or browse Examples
module tb;
  reg 	clk, rst;
  wire 	can_despatch;
  integer	i;
  reg [1:0] coin_stack [0:5] , coin;  
  always #10 clk = ~clk;  
  vending_machine u0 (can_despatch,clk,coin,rst);  
  initial begin
 $monitor("i=%0d, Time=%0d, reset=%b, coin=%b, can despatched=%b",i, $time, rst, coin, can_despatch);
$dumpfile("tb.vcd");
$dumpvars(1, tb);
  clk = 0;
    rst = 1;
   #50	    rst = 0;   
    coin_stack[0]=2'b00; // 0 rupee
    coin_stack[1]=2'b01; // 5 rupee
    coin_stack[2]=2'b10; //10 rupee
    coin_stack[3]=2'b01; // 5 rupee
    coin_stack[4]=2'b10; //10 rupee
    coin_stack[5]=2'b00; // 0 rupee
    i=0;
#130     $finish;    
 end  
always  @ (posedge clk)    begin	
coin = coin_stack[i];
i = i+1;
end    
endmodule

Vending machine/tb.vcd
$date
    Jun  3, 2023  14:43:40
$end
$version
    TOOL:	xmsim	20.09-s003
$end
$timescale
    1 ns
$end

$scope module tb $end
$var reg       1 !    clk $end
$var reg       1 "    rst $end
$var wire      1 #    can_despatch  $end
$var integer  32 $    i $end
$var reg       2 %    coin_stack[0] [1:0] $end
$var reg       2 &    coin_stack[1] [1:0] $end
$var reg       2 '    coin_stack[2] [1:0] $end
$var reg       2 (    coin_stack[3] [1:0] $end
$var reg       2 )    coin_stack[4] [1:0] $end
$var reg       2 *    coin_stack[5] [1:0] $end
$var reg       2 +    coin [1:0] $end
$upscope $end

$enddefinitions $end
$dumpvars
0!
1"
x#
bx $
bx %
bx &
bx '
bx (
bx )
bx *
bx +
$end
#10
1!
0#
#20
0!
#30
1!
#40
0!
#50
0"
b0 %
bx &
bx '
bx (
bx )
bx *
b0 %
b1 &
bx '
bx (
bx )
bx *
b0 %
b1 &
b10 '
bx (
bx )
bx *
b0 %
b1 &
b10 '
b1 (
bx )
bx *
b0 %
b1 &
b10 '
b1 (
b10 )
bx *
b0 %
b1 &
b10 '
b1 (
b10 )
b0 *
b0 $
1!
b0 +
b1 $
#60
0!
#70
1!
b1 +
b10 $
#80
0!
#90
1!
b10 +
b11 $
1#
#100
0!
#110
1!
b1 +
b100 $
0#
#120
0!
#130
1!
b10 +
b101 $
1#
#140
0!
#150
1!
b0 +
b110 $
0#
#160
0!
#170
1!
bx +
b111 $
